{
  "dependencies": [
    "Create Addons"
  ],
  "tasks": {},
  "rewards": {},
  "display": {
    "subtitle": {
      "text": ""
    },
    "description": [],
    "groups": {
      "Create Addons": {
        "position": [
          340,
          -35
        ]
      }
    },
    "icon": {
      "item": "create_so:polishing_wheel",
      "type": "heracles:item"
    },
    "icon_background": "heracles:textures/gui/quest_backgrounds/circles.png",
    "title": {
      "translate": "Sandpaper Overhaul"
    }
  },
  "settings": {
    "individual_progress": false,
    "hidden": false,
    "unlockNotification": false
  }
}